AUTHORS.rst
HISTORY.rst
LICENSE
MANIFEST.in
README.rst
setup.cfg
setup.py
docs/Makefile
docs/authors.rst
docs/conf.py
docs/contributing.rst
docs/history.rst
docs/index.rst
docs/installation.rst
docs/make.bat
docs/readme.rst
docs/usage.rst
pyho/__init__.py
pyho/pyho.py
pyho.egg-info/PKG-INFO
pyho.egg-info/SOURCES.txt
pyho.egg-info/dependency_links.txt
pyho.egg-info/not-zip-safe
pyho.egg-info/top_level.txt
tests/__init__.py
tests/test_pyho.py