Metadata-Version: 1.1
Name: pyho
Version: 0.1.0
Summary: PyHo does everything!  PyHo is a library of rresuable methods.
Home-page: https://github.com/jimmyho/pyho
Author: James Ho
Author-email: jho@neverlimited.uk
License: MIT license
Keywords: pyho
Platform: UNKNOWN
Classifier: Development Status :: 2 - Pre-Alpha
Classifier: Intended Audience :: Developers
Classifier: License :: OSI Approved :: MIT License
Classifier: Natural Language :: English
Classifier: Programming Language :: Python :: 2
Classifier: Programming Language :: Python :: 2.6
Classifier: Programming Language :: Python :: 2.7
Classifier: Programming Language :: Python :: 3
Classifier: Programming Language :: Python :: 3.3
Classifier: Programming Language :: Python :: 3.4
Classifier: Programming Language :: Python :: 3.5
